{
  "version": 1,
  "courses": [
    {
      "id": "electronic-circuits",
      "title": "电子电路基础及通信电子电路",
      "description": "从半导体器件到通信电子电路，按章节完成系统训练。",
      "chapters": [
        {
          "id": "chapter-1",
          "title": "第一章 半导体基础知识及二极管电路",
          "description": "半导体载流子、PN 结、二极管模型、整流与限幅电路。",
          "question_ids": [
            "1.1.1", "1.1.2", "1.2.1", "1.2.2", "1.2.3",
            "1.2.4", "1.2.5", "1.3.1", "1.3.2", "1.3.3",
            "1.3.4", "1.3.5", "1.3.6", "1.3.7", "1.3.8"
          ]
        }
      ]
    }
  ],
  "questions": [
    {
      "id": "1.1.1",
      "chapter_id": "chapter-1",
      "section": "1.1 半导体基础知识",
      "title": "P 型硅的载流子浓度",
      "prompt_markdown": "假设在硅材料的 P 型半导体中，受主杂质浓度为 \\(N_A=10^{23}\\,m^{-3}\\)。求该材料中的空穴浓度和电子浓度（\\(T=300K\\)）。",
      "figures": []
    },
    {
      "id": "1.1.2",
      "chapter_id": "chapter-1",
      "section": "1.1 半导体基础知识",
      "title": "温度对半导体导电性的影响",
      "prompt_markdown": "\\(T=300K\\) 时，硅的本征载流子浓度为 \\(n_i=1.5\\times10^{16}\\,m^{-3}\\)。\n\n1. 300K 时掺入受主杂质，\\(N_A=2\\times10^{20}\\,m^{-3}\\)，求空穴浓度和电子浓度。\n2. 温度升至 573K 时，\\(n_i\\approx3\\times10^{21}\\,m^{-3}\\)，掺杂浓度不变，问半导体呈何种导电性？",
      "figures": []
    },
    {
      "id": "1.2.1",
      "chapter_id": "chapter-1",
      "section": "1.2 PN 结与二极管",
      "title": "PN 结伏安特性计算",
      "prompt_markdown": "锗 PN 结在 \\(T=290K\\) 时：\n\n1. 反向电流达到饱和电流 \\(I_S\\) 的 90% 时，求反向电压。\n2. 正、反向电压都为 0.05V 时，求正、反向电流之比。\n3. 若 \\(I_S=1\\mu A\\)，求正向电压为 0.1V、0.2V、0.3V 时的电流。",
      "figures": []
    },
    {
      "id": "1.2.2",
      "chapter_id": "chapter-1",
      "section": "1.2 PN 结与二极管",
      "title": "锗、硅二极管串联",
      "prompt_markdown": "290K 时，锗、硅二极管的反向饱和电流分别为 \\(1nA\\)、\\(0.5pA\\)。两管串联，通过 1mA 正向电流，求各结电压。",
      "figures": [
        {
          "id": "fig_1_4_1",
          "alt": "锗二极管和硅二极管串联并通过 1mA 电流的电路图",
          "caption": "图 1.4.1  锗、硅二极管串联"
        }
      ]
    },
    {
      "id": "1.2.3",
      "chapter_id": "chapter-1",
      "section": "1.2 PN 结与二极管",
      "title": "二极管指数特性与万用表测量",
      "prompt_markdown": "二极管特性为 \\(I=20\\times10^{-12}(e^{V/26mV}-1)A\\)。\n\n1. 用 1.5V 干电池接在二极管两端，有多大电流？是否符合实际？\n2. 万用表测正向电阻时，R×10 挡读数较小而 R×100 挡读数较大，为什么？",
      "figures": []
    },
    {
      "id": "1.2.4",
      "chapter_id": "chapter-1",
      "section": "1.2 PN 结与二极管",
      "title": "稳压管稳压电路",
      "prompt_markdown": "硅稳压管电路中，\\(V_i=18V\\)、\\(R=1k\\Omega\\)、\\(R_L=2k\\Omega\\)、\\(V_Z=10V\\)，动态电阻和击穿前反向电流忽略。\n\n1. 求 \\(V_O,I_O,I,I_Z\\)。\n2. \\(R_L\\) 降低到多大时输出将不再稳定？",
      "figures": [
        {
          "id": "fig_1_4_3",
          "alt": "包含串联电阻、稳压二极管和负载的稳压电路",
          "caption": "图 1.4.3  稳压管稳压电路"
        }
      ]
    },
    {
      "id": "1.2.5",
      "chapter_id": "chapter-1",
      "section": "1.2 PN 结与二极管",
      "title": "稳压管限幅波形",
      "prompt_markdown": "稳压管 \\(V_Z=8V\\)，限流电阻 \\(R=3k\\Omega\\)，\\(u_i=15\\sin\\omega t\\,V\\)。画 \\(v_o(t)\\)。",
      "figures": [
        {
          "id": "fig_1_4_4",
          "alt": "稳压二极管并联在输出端的限幅电路",
          "caption": "图 1.4.4  稳压限幅电路"
        }
      ]
    },
    {
      "id": "1.3.1",
      "chapter_id": "chapter-1",
      "section": "1.3 二极管电路",
      "title": "静态电阻和动态电阻",
      "prompt_markdown": "某二极管伏安特性如图，求 a、b 点的静态电阻和动态电阻。",
      "figures": [
        {
          "id": "fig_1_4_6",
          "alt": "标注 a 点和 b 点的二极管伏安特性曲线",
          "caption": "图 1.4.6  二极管伏安特性曲线"
        }
      ]
    },
    {
      "id": "1.3.2",
      "chapter_id": "chapter-1",
      "section": "1.3 二极管电路",
      "title": "判断二极管工作状态",
      "prompt_markdown": "判断图中三个电路内二极管的导通、截止状态，并求 \\(V_P\\)。图 (a) 中导通压降取 0.3V；图 (b)、(c) 中二极管理想。",
      "figures": [
        {
          "id": "fig_1_4_7",
          "alt": "用于判断二极管状态的三组电路",
          "caption": "图 1.4.7  三组二极管状态判断电路"
        }
      ]
    },
    {
      "id": "1.3.3",
      "chapter_id": "chapter-1",
      "section": "1.3 二极管电路",
      "title": "桥式整流及故障分析",
      "prompt_markdown": "桥式整流电路中二极管均理想。求输出波形；若一管断路、极性接反、短路，各有什么后果？",
      "figures": [
        {
          "id": "fig_1_4_8",
          "alt": "变压器连接四只理想二极管组成的桥式整流电路",
          "caption": "图 1.4.8  桥式整流电路"
        }
      ]
    },
    {
      "id": "1.3.4",
      "chapter_id": "chapter-1",
      "section": "1.3 二极管电路",
      "title": "并联限幅电路",
      "prompt_markdown": "\\(u_g(t)=9\\sin\\omega t\\,V\\)。对图中的两个限幅电路画 \\(u_o(t)\\)。",
      "figures": [
        {
          "id": "fig_1_4_10",
          "alt": "两组带偏置电源的二极管限幅电路",
          "caption": "图 1.4.10  两组限幅电路"
        }
      ]
    },
    {
      "id": "1.3.5",
      "chapter_id": "chapter-1",
      "section": "1.3 二极管电路",
      "title": "串联双向限幅",
      "prompt_markdown": "串联双向限幅电路如图，输入为幅度 15V 的正弦电压，求 \\(u_o(t)\\)。",
      "figures": [
        {
          "id": "fig_1_4_12",
          "alt": "带 2V 和 10V 偏置支路的串联双向限幅电路",
          "caption": "图 1.4.12  串联双向限幅电路"
        }
      ]
    },
    {
      "id": "1.3.6",
      "chapter_id": "chapter-1",
      "section": "1.3 二极管电路",
      "title": "双二极管限幅模型",
      "prompt_markdown": "图中 \\(D_1,D_2\\) 为硅管，\\(u_i=6\\sin\\omega t\\,V\\)。分别用恒压降模型和分段线性模型（\\(V_{th}=0.5V,r_D=200\\Omega\\)）分析 \\(u_o\\) 波形。",
      "figures": [
        {
          "id": "fig_1_4_14",
          "alt": "两只方向相反的硅二极管并联构成的限幅电路",
          "caption": "图 1.4.14  双二极管限幅电路"
        }
      ]
    },
    {
      "id": "1.3.7",
      "chapter_id": "chapter-1",
      "section": "1.3 二极管电路",
      "title": "斜坡输入限幅",
      "prompt_markdown": "在 \\(0\\le t\\le10ms\\) 内，画出图中电路的 \\(u_o(t)\\)。分别采用理想模型和恒压降模型。",
      "figures": [
        {
          "id": "fig_1_4_16",
          "alt": "斜坡电压输入的二极管限幅电路及输入波形",
          "caption": "图 1.4.16  斜坡输入限幅电路"
        }
      ]
    },
    {
      "id": "1.3.8",
      "chapter_id": "chapter-1",
      "section": "1.3 二极管电路",
      "title": "二极管小信号分析",
      "prompt_markdown": "图中，常温 \\(V_T\\approx26mV\\)，阈值电压 \\(V_{th}=0.7V\\)，电容对交流信号视为短路，\\(u_i(t)=15\\sin\\omega t\\,mV\\)。\n\n1. \\(u_i=0\\) 时二极管电流和电压各为多少？\n2. 二极管交流电流 \\(i_d\\) 为多少？",
      "figures": [
        {
          "id": "fig_1_4_18",
          "alt": "包含耦合电容、偏置电阻和二极管的小信号电路",
          "caption": "图 1.4.18  二极管小信号电路"
        }
      ]
    }
  ]
}
